esetinspect/__init__.py
esetinspect/client.py
esetinspect/const.py
esetinspect/functions.py
esetinspect/models.py
esetinspect/py.typed
esetinspect-0.3.0.dist-info/LICENSE
esetinspect-0.3.0.dist-info/WHEEL
esetinspect-0.3.0.dist-info/METADATA
esetinspect-0.3.0.dist-info/RECORD
